__init__.py
bore/__init__.py
bore/__main__.py
bore/aio.py
bore/channel.py
bore/config.py
bore/env.py
bore/exceptions.py
bore/integrations.py
bore/logging.py
bore/middleware.py
bore/multipart.py
bore/schema.py
bore/sync.py
bore/terminal.py
bore/type.py
bore/utils.py
bore/abstractions/__init__.py
bore/abstractions/endpoint.py
bore/abstractions/function.py
bore/abstractions/image.py
bore/abstractions/map.py
bore/abstractions/mixins.py
bore/abstractions/output.py
bore/abstractions/pod.py
bore/abstractions/queue.py
bore/abstractions/sandbox.py
bore/abstractions/shell.py
bore/abstractions/taskqueue.py
bore/abstractions/volume.py
bore/abstractions/base/__init__.py
bore/abstractions/base/container.py
bore/abstractions/base/runner.py
bore/abstractions/experimental/__init__.py
bore/abstractions/experimental/signal.py
bore/abstractions/experimental/bot/__init__.py
bore/abstractions/experimental/bot/bot.py
bore/abstractions/experimental/bot/marker.py
bore/abstractions/experimental/bot/types.py
bore/abstractions/integrations/__init__.py
bore/abstractions/integrations/fastmcp.py
bore/abstractions/integrations/tts.py
bore/abstractions/integrations/tts_indextts.py
bore/abstractions/integrations/vllm.py
bore/cli/__init__.py
bore/cli/config.py
bore/cli/container.py
bore/cli/deployment.py
bore/cli/dev.py
bore/cli/extraclick.py
bore/cli/machine.py
bore/cli/main.py
bore/cli/pool.py
bore/cli/run.py
bore/cli/secret.py
bore/cli/serve.py
bore/cli/shell.py
bore/cli/task.py
bore/cli/token.py
bore/cli/volume.py
bore/cli/worker.py
bore/client/__init__.py
bore/client/client.py
bore/client/deployment.py
bore/client/task.py
bore/clients/__init__.py
bore/clients/bot/__init__.py
bore/clients/endpoint/__init__.py
bore/clients/function/__init__.py
bore/clients/gateway/__init__.py
bore/clients/google/__init__.py
bore/clients/google/api/__init__.py
bore/clients/image/__init__.py
bore/clients/map/__init__.py
bore/clients/output/__init__.py
bore/clients/pod/__init__.py
bore/clients/secret/__init__.py
bore_client-0.1.244.dist-info/METADATA
bore_client-0.1.244.dist-info/WHEEL
bore_client-0.1.244.dist-info/entry_points.txt
bore_client-0.1.244.dist-info/top_level.txt
bore_client-0.1.244.dist-info/RECORD
