Metadata-Version: 2.4
Name: bore-client
Version: 0.1.244
Author-email: "seg.console.wangsu.com" <support@wangsu.com>
Requires-Python: <4.0,>=3.8
Requires-Dist: typeguard<3.0.0,>=2.13.3
Requires-Dist: typing-extensions<5.0.0,>=4.7.1
Requires-Dist: grpclib<1.0.0,>=0.4.7
Requires-Dist: grpcio==1.69.0
Requires-Dist: asgiref<4.0.0,>=3.8.1
Requires-Dist: cloudpickle<4.0.0,>=3.0.0
Requires-Dist: rich<14.0.0,>=13.9.4
Requires-Dist: click<9.0.0,>=8.1.7
Requires-Dist: protobuf<5.0.0,>=4.25.1
Requires-Dist: fastapi<1.0.0,>=0.115.11
Requires-Dist: uvicorn<1.0.0,>=0.29.0
Requires-Dist: watchdog<5.0.0,>=4.0.0
Requires-Dist: betterproto-beta9[compiler]==2.0.1
Requires-Dist: croniter<4.0.0,>=3.0.3
Requires-Dist: websocket-client<2.0.0,>=1.8.0
Requires-Dist: prompt-toolkit<4.0.0,>=3.0.48
Requires-Dist: requests<3.0.0,>=2.32.3
Requires-Dist: paramiko<4.0.0,>=3.5.0
Requires-Dist: websockets<14,>=13
Requires-Dist: pyyaml<7.0.0,>=6.0.0
